<?xml version='1.0' encoding='UTF-8'?>
<SceneText>
  <Speakers>
    <Section>Speaker</Section>
    <Entry>
      <PointerOffset>283972</PointerOffset>
      <JapaneseText>魔女の声</JapaneseText>
      <EnglishText/>
      <Notes/>
      <Id>1</Id>
      <Status>To Do</Status>
    </Entry>
    <Entry>
      <PointerOffset/>
      <JapaneseText/>
      <EnglishText/>
      <Notes/>
      <Id>2</Id>
      <Status>ref:Speaker:8</Status>
    </Entry>
    <Entry>
      <PointerOffset/>
      <JapaneseText/>
      <EnglishText/>
      <Notes/>
      <Id>3</Id>
      <Status>ref:Speaker:19</Status>
    </Entry>
    <Entry>
      <PointerOffset>277980,278218,278283,278319,278390,278456,278495,278571,278642,278708,278719,278837,278923,279004,279080,279151,279217,279228,279397,279430,279441,279509,279545,279556,279627,279666,279677,279751,279793,279804,279847,279996,280032,280077,280134,280167,280208,280832,280843,280998,281106,281280,281356,281454,281560,281626,281679,281793,281990,282232,282297,282362,282427,283101,283442,283643,284543</PointerOffset>
      <JapaneseText>アルベルト</JapaneseText>
      <EnglishText/>
      <Notes/>
      <Id>4</Id>
      <Status>To Do</Status>
    </Entry>
    <Entry>
      <PointerOffset>279917,279969,280401,280986,281781,282084,282138,282194,282492,282540,282588,282642,282702,282756,282810,282913,282971,284610</PointerOffset>
      <JapaneseText>information</JapaneseText>
      <EnglishText/>
      <Notes/>
      <Id>5</Id>
      <Status>To Do</Status>
    </Entry>
    <Entry>
      <PointerOffset/>
      <JapaneseText/>
      <EnglishText/>
      <Notes/>
      <Id>6</Id>
      <Status>ref:Speaker:14</Status>
    </Entry>
  </Speakers>
  <Strings>
    <Section>Place</Section>
    <Entry>
      <PointerOffset>284524</PointerOffset>
      <JapaneseText>きらめきの塔　５階</JapaneseText>
      <EnglishText/>
      <Notes/>
      <Id>1</Id>
      <Status>To Do</Status>
    </Entry>
  </Strings>
  <Strings>
    <Section>Main</Section>
    <Entry>
      <PointerOffset>283976</PointerOffset>
      <VoiceId>&lt;audio:VSM_030_050_001&gt;</VoiceId>
      <JapaneseText></JapaneseText>
      <EnglishText/>
      <Notes/>
      <SpeakerId>1</SpeakerId>
      <Id>1</Id>
      <BubbleId>0</BubbleId>
      <Status>To Do</Status>
    </Entry>
    <Entry>
      <PointerOffset>283976</PointerOffset>
      <VoiceId>&lt;audio:VSM_030_050_002&gt;</VoiceId>
      <JapaneseText>今度の今度こそ
最後じゃあ！あ～もぉっ！
本当にこれで最後、
だかんね！！</JapaneseText>
      <EnglishText/>
      <Notes/>
      <SpeakerId>1</SpeakerId>
      <Id>1</Id>
      <BubbleId>1</BubbleId>
      <Status>To Do</Status>
    </Entry>
  </Strings>
  <Strings>
    <Section>Notice</Section>
    <Entry>
      <PointerOffset>277942</PointerOffset>
      <JapaneseText/>
      <EnglishText/>
      <Notes/>
      <Id>1</Id>
      <Status>ref:Notice:126</Status>
    </Entry>
    <Entry>
      <PointerOffset>277961</PointerOffset>
      <JapaneseText/>
      <EnglishText/>
      <Notes/>
      <Id>2</Id>
      <Status>ref:Notice:126</Status>
    </Entry>
    <Entry>
      <PointerOffset>277991</PointerOffset>
      <JapaneseText/>
      <EnglishText/>
      <Notes/>
      <Id>3</Id>
      <Status>ref:Notice:91</Status>
    </Entry>
    <Entry>
      <PointerOffset>278196</PointerOffset>
      <JapaneseText/>
      <EnglishText/>
      <Notes/>
      <Id>4</Id>
      <Status>ref:Notice:79</Status>
    </Entry>
    <Entry>
      <PointerOffset>278229</PointerOffset>
      <JapaneseText/>
      <EnglishText/>
      <Notes/>
      <Id>5</Id>
      <Status>ref:Notice:110</Status>
    </Entry>
    <Entry>
      <PointerOffset>278294</PointerOffset>
      <JapaneseText/>
      <EnglishText/>
      <Notes/>
      <Id>6</Id>
      <Status>ref:Notice:77</Status>
    </Entry>
    <Entry>
      <PointerOffset>278330</PointerOffset>
      <JapaneseText/>
      <EnglishText/>
      <Notes/>
      <Id>7</Id>
      <Status>ref:Notice:108</Status>
    </Entry>
    <Entry>
      <PointerOffset>278401</PointerOffset>
      <JapaneseText/>
      <EnglishText/>
      <Notes/>
      <Id>8</Id>
      <Status>ref:Notice:109</Status>
    </Entry>
    <Entry>
      <PointerOffset>278467</PointerOffset>
      <JapaneseText/>
      <EnglishText/>
      <Notes/>
      <Id>9</Id>
      <Status>ref:Notice:75</Status>
    </Entry>
    <Entry>
      <PointerOffset>278506</PointerOffset>
      <JapaneseText/>
      <EnglishText/>
      <Notes/>
      <Id>10</Id>
      <Status>ref:Notice:107</Status>
    </Entry>
    <Entry>
      <PointerOffset>278582</PointerOffset>
      <JapaneseText/>
      <EnglishText/>
      <Notes/>
      <Id>11</Id>
      <Status>ref:Notice:108</Status>
    </Entry>
    <Entry>
      <PointerOffset>278653</PointerOffset>
      <JapaneseText/>
      <EnglishText/>
      <Notes/>
      <Id>12</Id>
      <Status>ref:Notice:109</Status>
    </Entry>
    <Entry>
      <PointerOffset>278730</PointerOffset>
      <JapaneseText/>
      <EnglishText/>
      <Notes/>
      <Id>13</Id>
      <Status>ref:Notice:118</Status>
    </Entry>
    <Entry>
      <PointerOffset>278757</PointerOffset>
      <JapaneseText/>
      <EnglishText/>
      <Notes/>
      <Id>14</Id>
      <Status>ref:Notice:104</Status>
    </Entry>
    <Entry>
      <PointerOffset>278848</PointerOffset>
      <JapaneseText/>
      <EnglishText/>
      <Notes/>
      <Id>15</Id>
      <Status>ref:Notice:105</Status>
    </Entry>
    <Entry>
      <PointerOffset>278934</PointerOffset>
      <JapaneseText/>
      <EnglishText/>
      <Notes/>
      <Id>16</Id>
      <Status>ref:Notice:106</Status>
    </Entry>
    <Entry>
      <PointerOffset>279015</PointerOffset>
      <JapaneseText/>
      <EnglishText/>
      <Notes/>
      <Id>17</Id>
      <Status>ref:Notice:107</Status>
    </Entry>
    <Entry>
      <PointerOffset>279091</PointerOffset>
      <JapaneseText/>
      <EnglishText/>
      <Notes/>
      <Id>18</Id>
      <Status>ref:Notice:108</Status>
    </Entry>
    <Entry>
      <PointerOffset>279162</PointerOffset>
      <JapaneseText/>
      <EnglishText/>
      <Notes/>
      <Id>19</Id>
      <Status>ref:Notice:109</Status>
    </Entry>
    <Entry>
      <PointerOffset>279239</PointerOffset>
      <JapaneseText/>
      <EnglishText/>
      <Notes/>
      <Id>20</Id>
      <Status>ref:Notice:89</Status>
    </Entry>
    <Entry>
      <PointerOffset>279375</PointerOffset>
      <JapaneseText/>
      <EnglishText/>
      <Notes/>
      <Id>21</Id>
      <Status>ref:Notice:80</Status>
    </Entry>
    <Entry>
      <PointerOffset>279408</PointerOffset>
      <JapaneseText/>
      <EnglishText/>
      <Notes/>
      <Id>22</Id>
      <Status>ref:Notice:80</Status>
    </Entry>
    <Entry>
      <PointerOffset>279452</PointerOffset>
      <JapaneseText/>
      <EnglishText/>
      <Notes/>
      <Id>23</Id>
      <Status>ref:Notice:116</Status>
    </Entry>
    <Entry>
      <PointerOffset>278196</PointerOffset>
      <JapaneseText/>
      <EnglishText/>
      <Notes/>
      <Id>24</Id>
      <Status>ref:Notice:79</Status>
    </Entry>
    <Entry>
      <PointerOffset>278294</PointerOffset>
      <JapaneseText/>
      <EnglishText/>
      <Notes/>
      <Id>25</Id>
      <Status>ref:Notice:77</Status>
    </Entry>
    <Entry>
      <PointerOffset>279567</PointerOffset>
      <JapaneseText/>
      <EnglishText/>
      <Notes/>
      <Id>26</Id>
      <Status>ref:Notice:116</Status>
    </Entry>
    <Entry>
      <PointerOffset>279408</PointerOffset>
      <JapaneseText/>
      <EnglishText/>
      <Notes/>
      <Id>27</Id>
      <Status>ref:Notice:80</Status>
    </Entry>
    <Entry>
      <PointerOffset>279638</PointerOffset>
      <JapaneseText/>
      <EnglishText/>
      <Notes/>
      <Id>28</Id>
      <Status>ref:Notice:76</Status>
    </Entry>
    <Entry>
      <PointerOffset>279688</PointerOffset>
      <JapaneseText/>
      <EnglishText/>
      <Notes/>
      <Id>29</Id>
      <Status>ref:Notice:116</Status>
    </Entry>
    <Entry>
      <PointerOffset>278294</PointerOffset>
      <JapaneseText/>
      <EnglishText/>
      <Notes/>
      <Id>30</Id>
      <Status>ref:Notice:77</Status>
    </Entry>
    <Entry>
      <PointerOffset>278467</PointerOffset>
      <JapaneseText/>
      <EnglishText/>
      <Notes/>
      <Id>31</Id>
      <Status>ref:Notice:75</Status>
    </Entry>
    <Entry>
      <PointerOffset>279815</PointerOffset>
      <JapaneseText/>
      <EnglishText/>
      <Notes/>
      <Id>32</Id>
      <Status>ref:Notice:116</Status>
    </Entry>
    <Entry>
      <PointerOffset>279858</PointerOffset>
      <JapaneseText/>
      <EnglishText/>
      <Notes/>
      <Id>33</Id>
      <Status>ref:Notice:94</Status>
    </Entry>
    <Entry>
      <PointerOffset>279877</PointerOffset>
      <JapaneseText>&lt;DarkBlue&gt;&lt;WhiteOutline&gt;&lt;White&gt;&lt;NoOutline&gt;アイテムを取得しました！
%s×%d</JapaneseText>
      <EnglishText/>
      <Notes/>
      <SpeakerId>5</SpeakerId>
      <Id>34</Id>
      <Status>To Do</Status>
    </Entry>
    <Entry>
      <PointerOffset>279877</PointerOffset>
      <JapaneseText>&lt;DarkBlue&gt;&lt;WhiteOutline&gt;&lt;White&gt;&lt;NoOutline&gt;アイテムを取得しました！
%s×%d</JapaneseText>
      <EnglishText/>
      <Notes/>
      <SpeakerId>5</SpeakerId>
      <Id>35</Id>
      <Status>To Do</Status>
    </Entry>
    <Entry>
      <PointerOffset>279877</PointerOffset>
      <JapaneseText>&lt;DarkBlue&gt;&lt;WhiteOutline&gt;&lt;White&gt;&lt;NoOutline&gt;アイテムを取得しました！
%s×%d</JapaneseText>
      <EnglishText/>
      <Notes/>
      <SpeakerId>4</SpeakerId>
      <Id>36</Id>
      <Status>To Do</Status>
    </Entry>
    <Entry>
      <PointerOffset>280007</PointerOffset>
      <JapaneseText/>
      <EnglishText/>
      <Notes/>
      <Id>37</Id>
      <Status>ref:Notice:73</Status>
    </Entry>
    <Entry>
      <PointerOffset>279375</PointerOffset>
      <JapaneseText/>
      <EnglishText/>
      <Notes/>
      <Id>38</Id>
      <Status>ref:Notice:80</Status>
    </Entry>
    <Entry>
      <PointerOffset>279877</PointerOffset>
      <JapaneseText>&lt;DarkBlue&gt;&lt;WhiteOutline&gt;&lt;White&gt;&lt;NoOutline&gt;アイテムを取得しました！
%s×%d</JapaneseText>
      <EnglishText/>
      <Notes/>
      <SpeakerId>4</SpeakerId>
      <Id>39</Id>
      <Status>To Do</Status>
    </Entry>
    <Entry>
      <PointerOffset>279375</PointerOffset>
      <JapaneseText/>
      <EnglishText/>
      <Notes/>
      <Id>40</Id>
      <Status>ref:Notice:80</Status>
    </Entry>
    <Entry>
      <PointerOffset>279375</PointerOffset>
      <JapaneseText/>
      <EnglishText/>
      <Notes/>
      <Id>41</Id>
      <Status>ref:Notice:80</Status>
    </Entry>
    <Entry>
      <PointerOffset>280413</PointerOffset>
      <JapaneseText/>
      <EnglishText/>
      <Notes/>
      <Id>42</Id>
      <Status>ref:Notice:21</Status>
    </Entry>
    <Entry>
      <PointerOffset>280466</PointerOffset>
      <JapaneseText/>
      <EnglishText/>
      <Notes/>
      <Id>43</Id>
      <Status>ref:Notice:132</Status>
    </Entry>
    <Entry>
      <PointerOffset>280778</PointerOffset>
      <JapaneseText/>
      <EnglishText/>
      <Notes/>
      <Id>44</Id>
      <Status>ref:Notice:110</Status>
    </Entry>
    <Entry>
      <PointerOffset>280854</PointerOffset>
      <JapaneseText/>
      <EnglishText/>
      <Notes/>
      <Id>45</Id>
      <Status>ref:Notice:123</Status>
    </Entry>
    <Entry>
      <PointerOffset>278506</PointerOffset>
      <JapaneseText/>
      <EnglishText/>
      <Notes/>
      <Id>46</Id>
      <Status>ref:Notice:107</Status>
    </Entry>
    <Entry>
      <PointerOffset>281009</PointerOffset>
      <JapaneseText/>
      <EnglishText/>
      <Notes/>
      <Id>47</Id>
      <Status>ref:Notice:102</Status>
    </Entry>
    <Entry>
      <PointerOffset>281117</PointerOffset>
      <JapaneseText/>
      <EnglishText/>
      <Notes/>
      <Id>48</Id>
      <Status>ref:Notice:111</Status>
    </Entry>
    <Entry>
      <PointerOffset>281291</PointerOffset>
      <JapaneseText/>
      <EnglishText/>
      <Notes/>
      <Id>49</Id>
      <Status>ref:Notice:101</Status>
    </Entry>
    <Entry>
      <PointerOffset>281367</PointerOffset>
      <JapaneseText/>
      <EnglishText/>
      <Notes/>
      <Id>50</Id>
      <Status>ref:Notice:112</Status>
    </Entry>
    <Entry>
      <PointerOffset>281465</PointerOffset>
      <JapaneseText/>
      <EnglishText/>
      <Notes/>
      <Id>51</Id>
      <Status>ref:Notice:103</Status>
    </Entry>
    <Entry>
      <PointerOffset>281571</PointerOffset>
      <JapaneseText/>
      <EnglishText/>
      <Notes/>
      <Id>52</Id>
      <Status>ref:Notice:98</Status>
    </Entry>
    <Entry>
      <PointerOffset>281637</PointerOffset>
      <JapaneseText/>
      <EnglishText/>
      <Notes/>
      <Id>53</Id>
      <Status>ref:Notice:121</Status>
    </Entry>
    <Entry>
      <PointerOffset>281690</PointerOffset>
      <JapaneseText/>
      <EnglishText/>
      <Notes/>
      <Id>54</Id>
      <Status>ref:Notice:85</Status>
    </Entry>
    <Entry>
      <PointerOffset>278582</PointerOffset>
      <JapaneseText/>
      <EnglishText/>
      <Notes/>
      <Id>55</Id>
      <Status>ref:Notice:108</Status>
    </Entry>
    <Entry>
      <PointerOffset>281804</PointerOffset>
      <JapaneseText/>
      <EnglishText/>
      <Notes/>
      <Id>56</Id>
      <Status>ref:Notice:88</Status>
    </Entry>
    <Entry>
      <PointerOffset>282001</PointerOffset>
      <JapaneseText/>
      <EnglishText/>
      <Notes/>
      <Id>57</Id>
      <Status>ref:Notice:117</Status>
    </Entry>
    <Entry>
      <PointerOffset>282051</PointerOffset>
      <JapaneseText/>
      <EnglishText/>
      <Notes/>
      <Id>58</Id>
      <Status>ref:Notice:9</Status>
    </Entry>
    <Entry>
      <PointerOffset>282096</PointerOffset>
      <JapaneseText/>
      <EnglishText/>
      <Notes/>
      <Id>59</Id>
      <Status>ref:Notice:7</Status>
    </Entry>
    <Entry>
      <PointerOffset>282150</PointerOffset>
      <JapaneseText/>
      <EnglishText/>
      <Notes/>
      <Id>60</Id>
      <Status>ref:Notice:6</Status>
    </Entry>
    <Entry>
      <PointerOffset>282243</PointerOffset>
      <JapaneseText/>
      <EnglishText/>
      <Notes/>
      <Id>61</Id>
      <Status>ref:Notice:119</Status>
    </Entry>
    <Entry>
      <PointerOffset>282308</PointerOffset>
      <JapaneseText/>
      <EnglishText/>
      <Notes/>
      <Id>62</Id>
      <Status>ref:Notice:119</Status>
    </Entry>
    <Entry>
      <PointerOffset>282373</PointerOffset>
      <JapaneseText/>
      <EnglishText/>
      <Notes/>
      <Id>63</Id>
      <Status>ref:Notice:119</Status>
    </Entry>
    <Entry>
      <PointerOffset>282438</PointerOffset>
      <JapaneseText/>
      <EnglishText/>
      <Notes/>
      <Id>64</Id>
      <Status>ref:Notice:119</Status>
    </Entry>
    <Entry>
      <PointerOffset>282504</PointerOffset>
      <JapaneseText/>
      <EnglishText/>
      <Notes/>
      <Id>65</Id>
      <Status>ref:Notice:36</Status>
    </Entry>
    <Entry>
      <PointerOffset>282552</PointerOffset>
      <JapaneseText/>
      <EnglishText/>
      <Notes/>
      <Id>66</Id>
      <Status>ref:Notice:18</Status>
    </Entry>
    <Entry>
      <PointerOffset>282600</PointerOffset>
      <JapaneseText/>
      <EnglishText/>
      <Notes/>
      <Id>67</Id>
      <Status>ref:Notice:60</Status>
    </Entry>
    <Entry>
      <PointerOffset>282654</PointerOffset>
      <JapaneseText/>
      <EnglishText/>
      <Notes/>
      <Id>68</Id>
      <Status>ref:Notice:52</Status>
    </Entry>
    <Entry>
      <PointerOffset>282714</PointerOffset>
      <JapaneseText/>
      <EnglishText/>
      <Notes/>
      <Id>69</Id>
      <Status>ref:Notice:60</Status>
    </Entry>
    <Entry>
      <PointerOffset>282768</PointerOffset>
      <JapaneseText/>
      <EnglishText/>
      <Notes/>
      <Id>70</Id>
      <Status>ref:Notice:51</Status>
    </Entry>
    <Entry>
      <PointerOffset>282822</PointerOffset>
      <JapaneseText/>
      <EnglishText/>
      <Notes/>
      <Id>71</Id>
      <Status>ref:Notice:60</Status>
    </Entry>
    <Entry>
      <PointerOffset>282925</PointerOffset>
      <JapaneseText/>
      <EnglishText/>
      <Notes/>
      <Id>72</Id>
      <Status>ref:Notice:38</Status>
    </Entry>
    <Entry>
      <PointerOffset>282983</PointerOffset>
      <JapaneseText/>
      <EnglishText/>
      <Notes/>
      <Id>73</Id>
      <Status>ref:Notice:39</Status>
    </Entry>
    <Entry>
      <PointerOffset>283112</PointerOffset>
      <JapaneseText/>
      <EnglishText/>
      <Notes/>
      <Id>74</Id>
      <Status>ref:Notice:113</Status>
    </Entry>
    <Entry>
      <PointerOffset>283453</PointerOffset>
      <JapaneseText/>
      <EnglishText/>
      <Notes/>
      <Id>75</Id>
      <Status>ref:Notice:115</Status>
    </Entry>
    <Entry>
      <PointerOffset>283654</PointerOffset>
      <JapaneseText/>
      <EnglishText/>
      <Notes/>
      <Id>76</Id>
      <Status>ref:Notice:114</Status>
    </Entry>
    <Entry>
      <PointerOffset>284554</PointerOffset>
      <JapaneseText/>
      <EnglishText/>
      <Notes/>
      <Id>77</Id>
      <Status>ref:Notice:100</Status>
    </Entry>
    <Entry>
      <PointerOffset>284622</PointerOffset>
      <JapaneseText/>
      <EnglishText/>
      <Notes/>
      <Id>78</Id>
      <Status>ref:Notice:63</Status>
    </Entry>
  </Strings>
</SceneText>
